PygameCase/__init__.py
PygameCase/__version__.py
PygameCase/core.py
PygameDemo/__init__.py
PygameDemo/__version__.py
PygameDemo/core.py
pygame_demo/__init__.py
pygame_demo/__version__.py
pygame_demo/core.py
PygameCase-0.0.9.dist-info/LICENSE
PygameCase-0.0.9.dist-info/METADATA
PygameCase-0.0.9.dist-info/WHEEL
PygameCase-0.0.9.dist-info/top_level.txt
PygameCase-0.0.9.dist-info/RECORD
