Metadata-Version: 2.1
Name: PygameCase
Version: 0.0.9
Summary: AI悦创·玩中学，专属游戏代码。报名微信:Jiabcdefh
Home-page: https://github.com/AndersonHJB/pygame_demo
Author: Bornforthis
Author-email: bornforthis@bornforthis.cn
License: MIT
Classifier: License :: OSI Approved :: MIT License
Classifier: Programming Language :: Python
Classifier: Programming Language :: Python :: 3
Classifier: Programming Language :: Python :: 3.6
Classifier: Programming Language :: Python :: Implementation :: CPython
Classifier: Programming Language :: Python :: Implementation :: PyPy
Requires-Python: >=3.6.0
License-File: LICENSE
Requires-Dist: pygame
